[
  {
    "ID": "<NodeId: 93ff8675-afa6-468b-bec3-f8c95da867a0>",
    "lineno": 17,
    "tree": {
      "value": "+",
      "left": {
        "value": "az",
        "left": null,
        "right": null
      },
      "right": {
        "value": "bz",
        "left": null,
        "right": null
      }
    }
  },
  {
    "ID": "<NodeId: e10c1df0-7b23-4bb6-a0be-2f2d9fdb1013>",
    "lineno": 32,
    "tree": {
      "value": "+",
      "left": {
        "value": "i",
        "left": null,
        "right": null
      },
      "right": {
        "value": 1,
        "left": null,
        "right": null
      }
    }
  },
  {
    "ID": "<NodeId: c72b4ea8-d89f-4e7d-a534-b76605781632>",
    "lineno": 34,
    "tree": {
      "value": "+",
      "left": {
        "value": "x",
        "left": null,
        "right": null
      },
      "right": {
        "value": 0.001,
        "left": null,
        "right": null
      }
    }
  },
  {
    "ID": "<NodeId: 9729a6a7-d9bd-4b9f-aac2-55e996116957>",
    "lineno": 51,
    "tree": {
      "value": "+",
      "left": {
        "value": "i",
        "left": null,
        "right": null
      },
      "right": {
        "value": 1,
        "left": null,
        "right": null
      }
    }
  },
  {
    "ID": "<NodeId: 43c7a7ad-0291-4fdb-aed5-7ca1df752da2>",
    "lineno": 0,
    "tree": {
      "value": "%",
      "left": {
        "value": "i",
        "left": null,
        "right": null
      },
      "right": {
        "value": 2,
        "left": null,
        "right": null
      }
    }
  },
  {
    "ID": "<NodeId: ae830aad-a0ff-417e-bef8-4733ec738257>",
    "lineno": 55,
    "tree": {
      "value": "+",
      "left": {
        "value": "i",
        "left": null,
        "right": null
      },
      "right": {
        "value": 1,
        "left": null,
        "right": null
      }
    }
  },
  {
    "ID": "<NodeId: b076fe29-9f51-4e54-a5b4-13e3deb0c271>",
    "lineno": 56,
    "tree": {
      "value": "+",
      "left": {
        "value": "j",
        "left": null,
        "right": null
      },
      "right": {
        "value": 1,
        "left": null,
        "right": null
      }
    }
  },
  {
    "ID": "<NodeId: 64a2e053-ddfa-4dfd-87c8-5d6ba79e246d>",
    "lineno": 63,
    "tree": {
      "value": "+",
      "left": {
        "value": "i",
        "left": null,
        "right": null
      },
      "right": {
        "value": 1,
        "left": null,
        "right": null
      }
    }
  },
  {
    "ID": "<NodeId: 8989b134-d7e3-4756-bc3b-fedbbe6fe5c0>",
    "lineno": 88,
    "tree": {
      "value": "+",
      "left": {
        "value": "i",
        "left": null,
        "right": null
      },
      "right": {
        "value": 1,
        "left": null,
        "right": null
      }
    }
  },
  {
    "ID": "<NodeId: a0630fe5-bd89-47f4-b34d-7f41008189e3>",
    "lineno": 98,
    "tree": {
      "value": "+",
      "left": {
        "value": "i",
        "left": null,
        "right": null
      },
      "right": {
        "value": 1,
        "left": null,
        "right": null
      }
    }
  },
  {
    "ID": "<NodeId: e2584bf3-ba87-4fa9-b89f-31ccaf32cc89>",
    "lineno": 100,
    "tree": {
      "value": "+",
      "left": {
        "value": "i",
        "left": null,
        "right": null
      },
      "right": {
        "value": 1,
        "left": null,
        "right": null
      }
    }
  }
]